metabox/__init__.py
metabox/assembly.py
metabox/expansion.py
metabox/export.py
metabox/metrics.py
metabox/modeling.py
metabox/propagation.py
metabox/raster.py
metabox/rcwa.py
metabox/utils.py
metabox/material_data/GaN.csv
metabox/material_data/MoO3.csv
metabox/material_data/N-BK7.csv
metabox/material_data/Nb2O5.csv
metabox/material_data/Si3N4.csv
metabox/material_data/Si_ir.csv
metabox/material_data/Si_visible.csv
metabox/material_data/TiO2.csv
metabox/material_data/ZnO.csv
metabox/material_data/ZrO2.csv
metabox/material_data/quartz.csv
metabox/rcwa_tf/__init__.py
metabox/rcwa_tf/shane_rcwa_tf.py
metabox-0.0.3.dist-info/LICENSE.txt
metabox-0.0.3.dist-info/METADATA
metabox-0.0.3.dist-info/WHEEL
metabox-0.0.3.dist-info/top_level.txt
metabox-0.0.3.dist-info/RECORD
