Metadata-Version: 2.1
Name: metabox
Version: 0.0.3
Summary: A multi-scale optimization framework for diffractive optical systems.
Home-page: https://github.com/luochenghuang/metabox
Author: luochenghuang
Author-email: luocheng@uw.edu
License: MIT
Project-URL: Documentation, https://pyscaffold.org/
Platform: any
Classifier: Development Status :: 4 - Beta
Classifier: Programming Language :: Python
Requires-Python: >=3.8
License-File: LICENSE.txt
Requires-Dist: tensorflow
Requires-Dist: numpy
Requires-Dist: dill
Requires-Dist: tqdm
Requires-Dist: pandas
Requires-Dist: scipy
Requires-Dist: gdspy
Requires-Dist: matplotlib
Requires-Dist: pillow
Requires-Dist: importlib-metadata ; python_version < "3.8"
Provides-Extra: testing
Requires-Dist: setuptools ; extra == 'testing'
Requires-Dist: pytest ; extra == 'testing'
Requires-Dist: pytest-cov ; extra == 'testing'
